{
  "coletado_em": "2026-05-28 20:08:36",
  "servidores": {
    "Endora (PvP)": {
      "Experience": [
        {
          "Rank": 1,
          "PlayerId": 4552,
          "Name": "Tsukuyomi",
          "Level": 620,
          "Experience": 3946612237
        },
        {
          "Rank": 2,
          "PlayerId": 25730,
          "Name": "Warlord Oliveira",
          "Level": 582,
          "Experience": 3255017092
        },
        {
          "Rank": 3,
          "PlayerId": 260671,
          "Name": "Rellikk",
          "Level": 570,
          "Experience": 3055670810
        },
        {
          "Rank": 4,
          "PlayerId": 4641,
          "Name": "Seyuki",
          "Level": 566,
          "Experience": 2996145217
        },
        {
          "Rank": 5,
          "PlayerId": 262903,
          "Name": "Darkbaxie",
          "Level": 529,
          "Experience": 2449016776
        },
        {
          "Rank": 6,
          "PlayerId": 248907,
          "Name": "EvacinPro",
          "Level": 510,
          "Experience": 2186170311
        },
        {
          "Rank": 7,
          "PlayerId": 333670,
          "Name": "Louco Perigoso",
          "Level": 498,
          "Experience": 2037371976
        },
        {
          "Rank": 8,
          "PlayerId": 14767,
          "Name": "Lord Mandy Kai",
          "Level": 486,
          "Experience": 1890942897
        },
        {
          "Rank": 9,
          "PlayerId": 275952,
          "Name": "Demonix",
          "Level": 483,
          "Experience": 1856403409
        },
        {
          "Rank": 10,
          "PlayerId": 269283,
          "Name": "Jet Lag",
          "Level": 475,
          "Experience": 1768649558
        },
        {
          "Rank": 11,
          "PlayerId": 248791,
          "Name": "Migeehz",
          "Level": 470,
          "Experience": 1717195179
        },
        {
          "Rank": 12,
          "PlayerId": 318610,
          "Name": "Rama",
          "Level": 470,
          "Experience": 1716212841
        },
        {
          "Rank": 13,
          "PlayerId": 7063,
          "Name": "Unstoppable Guuh Zikaah",
          "Level": 468,
          "Experience": 1686664478
        },
        {
          "Rank": 14,
          "PlayerId": 248457,
          "Name": "angelmathias",
          "Level": 438,
          "Experience": 1382397464
        },
        {
          "Rank": 15,
          "PlayerId": 265774,
          "Name": "WanhedaDrago",
          "Level": 436,
          "Experience": 1371784344
        },
        {
          "Rank": 16,
          "PlayerId": 6109,
          "Name": "J O T A",
          "Level": 429,
          "Experience": 1298256482
        },
        {
          "Rank": 17,
          "PlayerId": 4560,
          "Name": "buKyk",
          "Level": 427,
          "Experience": 1279540120
        },
        {
          "Rank": 18,
          "PlayerId": 284765,
          "Name": "Amateratsu",
          "Level": 425,
          "Experience": 1265672935
        },
        {
          "Rank": 19,
          "PlayerId": 6368,
          "Name": "Unstoppable Nunoh",
          "Level": 423,
          "Experience": 1251252467
        },
        {
          "Rank": 20,
          "PlayerId": 243315,
          "Name": "teilor",
          "Level": 416,
          "Experience": 1189549466
        },
        {
          "Rank": 21,
          "PlayerId": 256753,
          "Name": "GANDALFFF",
          "Level": 412,
          "Experience": 1153378323
        },
        {
          "Rank": 22,
          "PlayerId": 260513,
          "Name": "Unstoppable Brandao",
          "Level": 409,
          "Experience": 1129195875
        },
        {
          "Rank": 23,
          "PlayerId": 11530,
          "Name": "Stenffor",
          "Level": 407,
          "Experience": 1107372646
        },
        {
          "Rank": 24,
          "PlayerId": 5463,
          "Name": "te comi",
          "Level": 401,
          "Experience": 1065750058
        },
        {
          "Rank": 25,
          "PlayerId": 25175,
          "Name": "Unstoppable Reirok",
          "Level": 400,
          "Experience": 1053861287
        },
        {
          "Rank": 26,
          "PlayerId": 4781,
          "Name": "GRETTEL",
          "Level": 394,
          "Experience": 1010759815
        },
        {
          "Rank": 27,
          "PlayerId": 263705,
          "Name": "papitafrita",
          "Level": 392,
          "Experience": 990875054
        },
        {
          "Rank": 28,
          "PlayerId": 291193,
          "Name": "Krynn",
          "Level": 387,
          "Experience": 957849423
        },
        {
          "Rank": 29,
          "PlayerId": 246166,
          "Name": "nanzin",
          "Level": 386,
          "Experience": 950781378
        },
        {
          "Rank": 30,
          "PlayerId": 280809,
          "Name": "anialex",
          "Level": 386,
          "Experience": 944308938
        },
        {
          "Rank": 31,
          "PlayerId": 8659,
          "Name": "Wezermoo",
          "Level": 376,
          "Experience": 876688682
        },
        {
          "Rank": 32,
          "PlayerId": 279224,
          "Name": "DemonicAV",
          "Level": 375,
          "Experience": 869442069
        },
        {
          "Rank": 33,
          "PlayerId": 4777,
          "Name": "MediCú",
          "Level": 373,
          "Experience": 856445419
        },
        {
          "Rank": 34,
          "PlayerId": 4565,
          "Name": "Sir Black",
          "Level": 372,
          "Experience": 846233169
        },
        {
          "Rank": 35,
          "PlayerId": 344475,
          "Name": "Rott",
          "Level": 367,
          "Experience": 812967039
        },
        {
          "Rank": 36,
          "PlayerId": 263704,
          "Name": "glad",
          "Level": 367,
          "Experience": 811272903
        },
        {
          "Rank": 37,
          "PlayerId": 263710,
          "Name": "ajolote",
          "Level": 365,
          "Experience": 799032565
        },
        {
          "Rank": 38,
          "PlayerId": 286578,
          "Name": "Tusa",
          "Level": 359,
          "Experience": 764018905
        },
        {
          "Rank": 39,
          "PlayerId": 28538,
          "Name": "Elmaniatico",
          "Level": 358,
          "Experience": 754849286
        },
        {
          "Rank": 40,
          "PlayerId": 248590,
          "Name": "killzero",
          "Level": 357,
          "Experience": 750337052
        },
        {
          "Rank": 41,
          "PlayerId": 355513,
          "Name": "Saci De Patinetii",
          "Level": 357,
          "Experience": 748718566
        },
        {
          "Rank": 42,
          "PlayerId": 278413,
          "Name": "Tokiio",
          "Level": 356,
          "Experience": 744664143
        },
        {
          "Rank": 43,
          "PlayerId": 288372,
          "Name": "Guardon",
          "Level": 352,
          "Experience": 714917406
        },
        {
          "Rank": 44,
          "PlayerId": 340696,
          "Name": "Killer Archer",
          "Level": 351,
          "Experience": 713530458
        },
        {
          "Rank": 45,
          "PlayerId": 356559,
          "Name": "TodMip",
          "Level": 351,
          "Experience": 710918893
        },
        {
          "Rank": 46,
          "PlayerId": 325430,
          "Name": "Pyroh",
          "Level": 351,
          "Experience": 710452148
        },
        {
          "Rank": 47,
          "PlayerId": 255763,
          "Name": "Uss samsomp",
          "Level": 351,
          "Experience": 709767326
        },
        {
          "Rank": 48,
          "PlayerId": 340645,
          "Name": "EmmgeKiller",
          "Level": 349,
          "Experience": 697996727
        },
        {
          "Rank": 49,
          "PlayerId": 273255,
          "Name": "MorilIa",
          "Level": 347,
          "Experience": 684621138
        },
        {
          "Rank": 50,
          "PlayerId": 269891,
          "Name": "nieves",
          "Level": 345,
          "Experience": 673786390
        }
      ],
      "Melee": [
        {
          "Rank": 1,
          "PlayerId": 275952,
          "Name": "Demonix",
          "Level": 87,
          "Experience": 6779540
        },
        {
          "Rank": 2,
          "PlayerId": 4641,
          "Name": "Seyuki",
          "Level": 84,
          "Experience": 5012665
        },
        {
          "Rank": 3,
          "PlayerId": 248907,
          "Name": "EvacinPro",
          "Level": 80,
          "Experience": 3204599
        },
        {
          "Rank": 4,
          "PlayerId": 4565,
          "Name": "Sir Black",
          "Level": 78,
          "Experience": 2632935
        },
        {
          "Rank": 5,
          "PlayerId": 235261,
          "Name": "Heir of Light",
          "Level": 72,
          "Experience": 1361182
        },
        {
          "Rank": 6,
          "PlayerId": 14253,
          "Name": "Aaunn",
          "Level": 72,
          "Experience": 1341276
        },
        {
          "Rank": 7,
          "PlayerId": 357844,
          "Name": "xTRONx",
          "Level": 71,
          "Experience": 1198140
        },
        {
          "Rank": 8,
          "PlayerId": 338677,
          "Name": "Holani",
          "Level": 71,
          "Experience": 1139765
        },
        {
          "Rank": 9,
          "PlayerId": 4560,
          "Name": "buKyk",
          "Level": 70,
          "Experience": 1023317
        },
        {
          "Rank": 10,
          "PlayerId": 5463,
          "Name": "te comi",
          "Level": 69,
          "Experience": 990429
        },
        {
          "Rank": 11,
          "PlayerId": 6368,
          "Name": "Unstoppable Nunoh",
          "Level": 69,
          "Experience": 941065
        },
        {
          "Rank": 12,
          "PlayerId": 246441,
          "Name": "DAYA",
          "Level": 69,
          "Experience": 904285
        },
        {
          "Rank": 13,
          "PlayerId": 347251,
          "Name": "LIRǟnzɛsLIxD",
          "Level": 68,
          "Experience": 856427
        },
        {
          "Rank": 14,
          "PlayerId": 29509,
          "Name": "Yalel",
          "Level": 68,
          "Experience": 855124
        },
        {
          "Rank": 15,
          "PlayerId": 11924,
          "Name": "MARECHALIGRISs",
          "Level": 66,
          "Experience": 654449
        },
        {
          "Rank": 16,
          "PlayerId": 320811,
          "Name": "Olberdam",
          "Level": 64,
          "Experience": 560973
        },
        {
          "Rank": 17,
          "PlayerId": 6642,
          "Name": "King Maniiak",
          "Level": 64,
          "Experience": 540297
        },
        {
          "Rank": 18,
          "PlayerId": 272793,
          "Name": "Syer D",
          "Level": 63,
          "Experience": 501273
        },
        {
          "Rank": 19,
          "PlayerId": 21192,
          "Name": "zkweF",
          "Level": 63,
          "Experience": 488298
        },
        {
          "Rank": 20,
          "PlayerId": 4782,
          "Name": "KingTar",
          "Level": 63,
          "Experience": 479281
        },
        {
          "Rank": 21,
          "PlayerId": 317552,
          "Name": "Paladina AL",
          "Level": 63,
          "Experience": 471423
        },
        {
          "Rank": 22,
          "PlayerId": 10894,
          "Name": "Tarekziad",
          "Level": 63,
          "Experience": 462055
        },
        {
          "Rank": 23,
          "PlayerId": 242656,
          "Name": "Monarch Ashborn",
          "Level": 63,
          "Experience": 460333
        },
        {
          "Rank": 24,
          "PlayerId": 362485,
          "Name": "Khaziks",
          "Level": 62,
          "Experience": 453810
        },
        {
          "Rank": 25,
          "PlayerId": 268424,
          "Name": "milhouseblac",
          "Level": 62,
          "Experience": 442561
        },
        {
          "Rank": 26,
          "PlayerId": 365929,
          "Name": "KingThorn",
          "Level": 62,
          "Experience": 440081
        },
        {
          "Rank": 27,
          "PlayerId": 240485,
          "Name": "shadowIxD",
          "Level": 62,
          "Experience": 438671
        },
        {
          "Rank": 28,
          "PlayerId": 4800,
          "Name": "Morbiidb",
          "Level": 62,
          "Experience": 432888
        },
        {
          "Rank": 29,
          "PlayerId": 326214,
          "Name": "Death Vader",
          "Level": 62,
          "Experience": 430108
        },
        {
          "Rank": 30,
          "PlayerId": 8659,
          "Name": "Wezermoo",
          "Level": 61,
          "Experience": 400666
        },
        {
          "Rank": 31,
          "PlayerId": 238837,
          "Name": "raduref",
          "Level": 61,
          "Experience": 383263
        },
        {
          "Rank": 32,
          "PlayerId": 310173,
          "Name": "OHemgkiller",
          "Level": 61,
          "Experience": 377916
        },
        {
          "Rank": 33,
          "PlayerId": 266584,
          "Name": "ItzLegend",
          "Level": 61,
          "Experience": 374748
        },
        {
          "Rank": 34,
          "PlayerId": 315466,
          "Name": "Kroger",
          "Level": 61,
          "Experience": 370669
        },
        {
          "Rank": 35,
          "PlayerId": 297229,
          "Name": "Bankodzu",
          "Level": 61,
          "Experience": 367106
        },
        {
          "Rank": 36,
          "PlayerId": 249534,
          "Name": "Wolfer",
          "Level": 60,
          "Experience": 357995
        },
        {
          "Rank": 37,
          "PlayerId": 5358,
          "Name": "AssisZika",
          "Level": 60,
          "Experience": 348458
        },
        {
          "Rank": 38,
          "PlayerId": 326169,
          "Name": "Kraox",
          "Level": 60,
          "Experience": 344612
        },
        {
          "Rank": 39,
          "PlayerId": 303873,
          "Name": "LuisaoTV",
          "Level": 60,
          "Experience": 330358
        },
        {
          "Rank": 40,
          "PlayerId": 283306,
          "Name": "Zzangetsu",
          "Level": 60,
          "Experience": 323594
        },
        {
          "Rank": 41,
          "PlayerId": 278296,
          "Name": "Gimpyhero",
          "Level": 59,
          "Experience": 301821
        },
        {
          "Rank": 42,
          "PlayerId": 257008,
          "Name": "orm",
          "Level": 59,
          "Experience": 299382
        },
        {
          "Rank": 43,
          "PlayerId": 239488,
          "Name": "yundi",
          "Level": 59,
          "Experience": 291736
        },
        {
          "Rank": 44,
          "PlayerId": 235862,
          "Name": "Litchgostin",
          "Level": 58,
          "Experience": 277612
        },
        {
          "Rank": 45,
          "PlayerId": 267009,
          "Name": "Sabalero",
          "Level": 58,
          "Experience": 274003
        },
        {
          "Rank": 46,
          "PlayerId": 360547,
          "Name": "RhasGhaKu",
          "Level": 58,
          "Experience": 273479
        },
        {
          "Rank": 47,
          "PlayerId": 19941,
          "Name": "faya",
          "Level": 58,
          "Experience": 273385
        },
        {
          "Rank": 48,
          "PlayerId": 344365,
          "Name": "Drakants",
          "Level": 58,
          "Experience": 271613
        },
        {
          "Rank": 49,
          "PlayerId": 257280,
          "Name": "Drilo",
          "Level": 58,
          "Experience": 258827
        },
        {
          "Rank": 50,
          "PlayerId": 237591,
          "Name": "leonstark",
          "Level": 57,
          "Experience": 249031
        }
      ],
      "Shielding": [
        {
          "Rank": 1,
          "PlayerId": 4641,
          "Name": "Seyuki",
          "Level": 76,
          "Experience": 4068041
        },
        {
          "Rank": 2,
          "PlayerId": 275952,
          "Name": "Demonix",
          "Level": 73,
          "Experience": 3128456
        },
        {
          "Rank": 3,
          "PlayerId": 25730,
          "Name": "Warlord Oliveira",
          "Level": 26,
          "Experience": 2141554
        },
        {
          "Rank": 4,
          "PlayerId": 4565,
          "Name": "Sir Black",
          "Level": 69,
          "Experience": 1918498
        },
        {
          "Rank": 5,
          "PlayerId": 357844,
          "Name": "xTRONx",
          "Level": 69,
          "Experience": 1855925
        },
        {
          "Rank": 6,
          "PlayerId": 248907,
          "Name": "EvacinPro",
          "Level": 68,
          "Experience": 1789286
        },
        {
          "Rank": 7,
          "PlayerId": 248791,
          "Name": "Migeehz",
          "Level": 26,
          "Experience": 1663585
        },
        {
          "Rank": 8,
          "PlayerId": 365641,
          "Name": "Ruphire",
          "Level": 26,
          "Experience": 1619074
        },
        {
          "Rank": 9,
          "PlayerId": 262903,
          "Name": "Darkbaxie",
          "Level": 25,
          "Experience": 1355796
        },
        {
          "Rank": 10,
          "PlayerId": 14253,
          "Name": "Aaunn",
          "Level": 66,
          "Experience": 1285638
        },
        {
          "Rank": 11,
          "PlayerId": 333670,
          "Name": "Louco Perigoso",
          "Level": 25,
          "Experience": 1230655
        },
        {
          "Rank": 12,
          "PlayerId": 11530,
          "Name": "Stenffor",
          "Level": 25,
          "Experience": 1195055
        },
        {
          "Rank": 13,
          "PlayerId": 338677,
          "Name": "Holani",
          "Level": 64,
          "Experience": 1135150
        },
        {
          "Rank": 14,
          "PlayerId": 4560,
          "Name": "buKyk",
          "Level": 62,
          "Experience": 872850
        },
        {
          "Rank": 15,
          "PlayerId": 5463,
          "Name": "te comi",
          "Level": 62,
          "Experience": 863690
        },
        {
          "Rank": 16,
          "PlayerId": 6368,
          "Name": "Unstoppable Nunoh",
          "Level": 62,
          "Experience": 829792
        },
        {
          "Rank": 17,
          "PlayerId": 29509,
          "Name": "Yalel",
          "Level": 61,
          "Experience": 799661
        },
        {
          "Rank": 18,
          "PlayerId": 246441,
          "Name": "DAYA",
          "Level": 61,
          "Experience": 775343
        },
        {
          "Rank": 19,
          "PlayerId": 344475,
          "Name": "Rott",
          "Level": 24,
          "Experience": 751037
        },
        {
          "Rank": 20,
          "PlayerId": 235261,
          "Name": "Heir of Light",
          "Level": 60,
          "Experience": 706919
        },
        {
          "Rank": 21,
          "PlayerId": 4655,
          "Name": "AgilitBoss",
          "Level": 24,
          "Experience": 702831
        },
        {
          "Rank": 22,
          "PlayerId": 4745,
          "Name": "Eldermolidor",
          "Level": 23,
          "Experience": 594443
        },
        {
          "Rank": 23,
          "PlayerId": 8659,
          "Name": "Wezermoo",
          "Level": 59,
          "Experience": 586946
        },
        {
          "Rank": 24,
          "PlayerId": 347251,
          "Name": "LIRǟnzɛsLIxD",
          "Level": 58,
          "Experience": 574401
        },
        {
          "Rank": 25,
          "PlayerId": 325430,
          "Name": "Pyroh",
          "Level": 23,
          "Experience": 564405
        },
        {
          "Rank": 26,
          "PlayerId": 269283,
          "Name": "Jet Lag",
          "Level": 23,
          "Experience": 548874
        },
        {
          "Rank": 27,
          "PlayerId": 298742,
          "Name": "joseguevami",
          "Level": 23,
          "Experience": 526640
        },
        {
          "Rank": 28,
          "PlayerId": 14767,
          "Name": "Lord Mandy Kai",
          "Level": 23,
          "Experience": 523430
        },
        {
          "Rank": 29,
          "PlayerId": 317552,
          "Name": "Paladina AL",
          "Level": 57,
          "Experience": 510304
        },
        {
          "Rank": 30,
          "PlayerId": 256753,
          "Name": "GANDALFFF",
          "Level": 23,
          "Experience": 509591
        },
        {
          "Rank": 31,
          "PlayerId": 6109,
          "Name": "J O T A",
          "Level": 23,
          "Experience": 496890
        },
        {
          "Rank": 32,
          "PlayerId": 21192,
          "Name": "zkweF",
          "Level": 57,
          "Experience": 482746
        },
        {
          "Rank": 33,
          "PlayerId": 355591,
          "Name": "YISÚS",
          "Level": 23,
          "Experience": 479231
        },
        {
          "Rank": 34,
          "PlayerId": 6642,
          "Name": "King Maniiak",
          "Level": 56,
          "Experience": 423404
        },
        {
          "Rank": 35,
          "PlayerId": 272793,
          "Name": "Syer D",
          "Level": 56,
          "Experience": 423373
        },
        {
          "Rank": 36,
          "PlayerId": 242656,
          "Name": "Monarch Ashborn",
          "Level": 56,
          "Experience": 420375
        },
        {
          "Rank": 37,
          "PlayerId": 335296,
          "Name": "Jceriu",
          "Level": 23,
          "Experience": 419633
        },
        {
          "Rank": 38,
          "PlayerId": 4800,
          "Name": "Morbiidb",
          "Level": 56,
          "Experience": 417119
        },
        {
          "Rank": 39,
          "PlayerId": 268424,
          "Name": "milhouseblac",
          "Level": 56,
          "Experience": 415597
        },
        {
          "Rank": 40,
          "PlayerId": 240485,
          "Name": "shadowIxD",
          "Level": 56,
          "Experience": 413782
        },
        {
          "Rank": 41,
          "PlayerId": 310173,
          "Name": "OHemgkiller",
          "Level": 55,
          "Experience": 404408
        },
        {
          "Rank": 42,
          "PlayerId": 10894,
          "Name": "Tarekziad",
          "Level": 55,
          "Experience": 402666
        },
        {
          "Rank": 43,
          "PlayerId": 320811,
          "Name": "Olberdam",
          "Level": 55,
          "Experience": 401698
        },
        {
          "Rank": 44,
          "PlayerId": 11924,
          "Name": "MARECHALIGRISs",
          "Level": 55,
          "Experience": 390994
        },
        {
          "Rank": 45,
          "PlayerId": 4777,
          "Name": "MediCú",
          "Level": 23,
          "Experience": 384212
        },
        {
          "Rank": 46,
          "PlayerId": 238837,
          "Name": "raduref",
          "Level": 55,
          "Experience": 374908
        },
        {
          "Rank": 47,
          "PlayerId": 266584,
          "Name": "ItzLegend",
          "Level": 55,
          "Experience": 367974
        },
        {
          "Rank": 48,
          "PlayerId": 315466,
          "Name": "Kroger",
          "Level": 54,
          "Experience": 359460
        },
        {
          "Rank": 49,
          "PlayerId": 297229,
          "Name": "Bankodzu",
          "Level": 54,
          "Experience": 347876
        },
        {
          "Rank": 50,
          "PlayerId": 326214,
          "Name": "Death Vader",
          "Level": 54,
          "Experience": 340197
        }
      ],
      "Magic": [
        {
          "Rank": 1,
          "PlayerId": 248791,
          "Name": "Migeehz",
          "Level": 78,
          "Experience": 3096461
        },
        {
          "Rank": 2,
          "PlayerId": 25730,
          "Name": "Warlord Oliveira",
          "Level": 77,
          "Experience": 2655177
        },
        {
          "Rank": 3,
          "PlayerId": 262903,
          "Name": "Darkbaxie",
          "Level": 75,
          "Experience": 2277262
        },
        {
          "Rank": 4,
          "PlayerId": 333670,
          "Name": "Louco Perigoso",
          "Level": 75,
          "Experience": 2204611
        },
        {
          "Rank": 5,
          "PlayerId": 11530,
          "Name": "Stenffor",
          "Level": 75,
          "Experience": 2195729
        },
        {
          "Rank": 6,
          "PlayerId": 4641,
          "Name": "Seyuki",
          "Level": 16,
          "Experience": 1985377
        },
        {
          "Rank": 7,
          "PlayerId": 269283,
          "Name": "Jet Lag",
          "Level": 69,
          "Experience": 1190341
        },
        {
          "Rank": 8,
          "PlayerId": 344475,
          "Name": "Rott",
          "Level": 69,
          "Experience": 1151000
        },
        {
          "Rank": 9,
          "PlayerId": 325430,
          "Name": "Pyroh",
          "Level": 68,
          "Experience": 1021000
        },
        {
          "Rank": 10,
          "PlayerId": 14767,
          "Name": "Lord Mandy Kai",
          "Level": 67,
          "Experience": 919935
        },
        {
          "Rank": 11,
          "PlayerId": 256753,
          "Name": "GANDALFFF",
          "Level": 66,
          "Experience": 833788
        },
        {
          "Rank": 12,
          "PlayerId": 263704,
          "Name": "glad",
          "Level": 66,
          "Experience": 790275
        },
        {
          "Rank": 13,
          "PlayerId": 4777,
          "Name": "MediCú",
          "Level": 65,
          "Experience": 765150
        },
        {
          "Rank": 14,
          "PlayerId": 4655,
          "Name": "AgilitBoss",
          "Level": 65,
          "Experience": 729590
        },
        {
          "Rank": 15,
          "PlayerId": 4565,
          "Name": "Sir Black",
          "Level": 15,
          "Experience": 694927
        },
        {
          "Rank": 16,
          "PlayerId": 306829,
          "Name": "Eimykiller",
          "Level": 65,
          "Experience": 686254
        },
        {
          "Rank": 17,
          "PlayerId": 255026,
          "Name": "bebesitó",
          "Level": 64,
          "Experience": 670650
        },
        {
          "Rank": 18,
          "PlayerId": 348793,
          "Name": "īDãrk fåmâ",
          "Level": 64,
          "Experience": 664690
        },
        {
          "Rank": 19,
          "PlayerId": 298742,
          "Name": "joseguevami",
          "Level": 64,
          "Experience": 653399
        },
        {
          "Rank": 20,
          "PlayerId": 355591,
          "Name": "YISÚS",
          "Level": 64,
          "Experience": 639766
        },
        {
          "Rank": 21,
          "PlayerId": 6109,
          "Name": "J O T A",
          "Level": 63,
          "Experience": 598871
        },
        {
          "Rank": 22,
          "PlayerId": 273287,
          "Name": "XxGodlikexX",
          "Level": 63,
          "Experience": 547447
        },
        {
          "Rank": 23,
          "PlayerId": 340645,
          "Name": "EmmgeKiller",
          "Level": 62,
          "Experience": 522498
        },
        {
          "Rank": 24,
          "PlayerId": 235607,
          "Name": "Killirmico",
          "Level": 62,
          "Experience": 505349
        },
        {
          "Rank": 25,
          "PlayerId": 279224,
          "Name": "DemonicAV",
          "Level": 62,
          "Experience": 502522
        },
        {
          "Rank": 26,
          "PlayerId": 353942,
          "Name": "OSHIMARU",
          "Level": 61,
          "Experience": 483694
        },
        {
          "Rank": 27,
          "PlayerId": 288372,
          "Name": "Guardon",
          "Level": 61,
          "Experience": 481537
        },
        {
          "Rank": 28,
          "PlayerId": 278698,
          "Name": "Zynthrox",
          "Level": 61,
          "Experience": 476316
        },
        {
          "Rank": 29,
          "PlayerId": 348473,
          "Name": "Xulita",
          "Level": 61,
          "Experience": 472162
        },
        {
          "Rank": 30,
          "PlayerId": 347001,
          "Name": "Stay Awake",
          "Level": 61,
          "Experience": 465544
        },
        {
          "Rank": 31,
          "PlayerId": 259894,
          "Name": "wiltr",
          "Level": 61,
          "Experience": 449505
        },
        {
          "Rank": 32,
          "PlayerId": 351776,
          "Name": "Yeoshen",
          "Level": 61,
          "Experience": 445427
        },
        {
          "Rank": 33,
          "PlayerId": 335296,
          "Name": "Jceriu",
          "Level": 60,
          "Experience": 422536
        },
        {
          "Rank": 34,
          "PlayerId": 21610,
          "Name": "Aelar",
          "Level": 60,
          "Experience": 422396
        },
        {
          "Rank": 35,
          "PlayerId": 269891,
          "Name": "nieves",
          "Level": 60,
          "Experience": 415350
        },
        {
          "Rank": 36,
          "PlayerId": 279130,
          "Name": "midado",
          "Level": 60,
          "Experience": 409197
        },
        {
          "Rank": 37,
          "PlayerId": 7405,
          "Name": "Arghos",
          "Level": 60,
          "Experience": 396693
        },
        {
          "Rank": 38,
          "PlayerId": 24112,
          "Name": "DevPHP",
          "Level": 60,
          "Experience": 391030
        },
        {
          "Rank": 39,
          "PlayerId": 354977,
          "Name": "Renatox",
          "Level": 59,
          "Experience": 369747
        },
        {
          "Rank": 40,
          "PlayerId": 337688,
          "Name": "Jrdp",
          "Level": 59,
          "Experience": 355075
        },
        {
          "Rank": 41,
          "PlayerId": 360570,
          "Name": "CharlieLionn",
          "Level": 59,
          "Experience": 348378
        },
        {
          "Rank": 42,
          "PlayerId": 255763,
          "Name": "Uss samsomp",
          "Level": 59,
          "Experience": 348167
        },
        {
          "Rank": 43,
          "PlayerId": 352903,
          "Name": "LOCAZUNE",
          "Level": 58,
          "Experience": 342396
        },
        {
          "Rank": 44,
          "PlayerId": 292508,
          "Name": "Halpyir",
          "Level": 58,
          "Experience": 324314
        },
        {
          "Rank": 45,
          "PlayerId": 318068,
          "Name": "charol",
          "Level": 58,
          "Experience": 322172
        },
        {
          "Rank": 46,
          "PlayerId": 4745,
          "Name": "Eldermolidor",
          "Level": 58,
          "Experience": 316569
        },
        {
          "Rank": 47,
          "PlayerId": 367770,
          "Name": "Lymonada",
          "Level": 58,
          "Experience": 308006
        },
        {
          "Rank": 48,
          "PlayerId": 250302,
          "Name": "rancla",
          "Level": 57,
          "Experience": 299237
        },
        {
          "Rank": 49,
          "PlayerId": 4552,
          "Name": "Tsukuyomi",
          "Level": 25,
          "Experience": 282610
        },
        {
          "Rank": 50,
          "PlayerId": 351384,
          "Name": "billiexøxø",
          "Level": 57,
          "Experience": 277265
        }
      ],
      "Distance": [
        {
          "Rank": 1,
          "PlayerId": 260671,
          "Name": "Rellikk",
          "Level": 84,
          "Experience": 2852668
        },
        {
          "Rank": 2,
          "PlayerId": 4552,
          "Name": "Tsukuyomi",
          "Level": 82,
          "Experience": 2453136
        },
        {
          "Rank": 3,
          "PlayerId": 248457,
          "Name": "angelmathias",
          "Level": 79,
          "Experience": 1642981
        },
        {
          "Rank": 4,
          "PlayerId": 331661,
          "Name": "Monstrao",
          "Level": 78,
          "Experience": 1623147
        },
        {
          "Rank": 5,
          "PlayerId": 246166,
          "Name": "nanzin",
          "Level": 76,
          "Experience": 1219127
        },
        {
          "Rank": 6,
          "PlayerId": 357863,
          "Name": "Bredac",
          "Level": 75,
          "Experience": 1173875
        },
        {
          "Rank": 7,
          "PlayerId": 243315,
          "Name": "teilor",
          "Level": 75,
          "Experience": 1168116
        },
        {
          "Rank": 8,
          "PlayerId": 7063,
          "Name": "Unstoppable Guuh Zikaah",
          "Level": 75,
          "Experience": 1166267
        },
        {
          "Rank": 9,
          "PlayerId": 341643,
          "Name": "Blok",
          "Level": 75,
          "Experience": 1158724
        },
        {
          "Rank": 10,
          "PlayerId": 4781,
          "Name": "GRETTEL",
          "Level": 74,
          "Experience": 1037763
        },
        {
          "Rank": 11,
          "PlayerId": 23269,
          "Name": "Dex",
          "Level": 74,
          "Experience": 1034184
        },
        {
          "Rank": 12,
          "PlayerId": 28538,
          "Name": "Elmaniatico",
          "Level": 74,
          "Experience": 975072
        },
        {
          "Rank": 13,
          "PlayerId": 333468,
          "Name": "jaka",
          "Level": 74,
          "Experience": 942695
        },
        {
          "Rank": 14,
          "PlayerId": 284765,
          "Name": "Amateratsu",
          "Level": 73,
          "Experience": 867130
        },
        {
          "Rank": 15,
          "PlayerId": 286578,
          "Name": "Tusa",
          "Level": 73,
          "Experience": 864381
        },
        {
          "Rank": 16,
          "PlayerId": 340696,
          "Name": "Killer Archer",
          "Level": 73,
          "Experience": 858227
        },
        {
          "Rank": 17,
          "PlayerId": 280809,
          "Name": "anialex",
          "Level": 73,
          "Experience": 845947
        },
        {
          "Rank": 18,
          "PlayerId": 318610,
          "Name": "Rama",
          "Level": 73,
          "Experience": 844350
        },
        {
          "Rank": 19,
          "PlayerId": 313192,
          "Name": "EVIL HERO",
          "Level": 72,
          "Experience": 792592
        },
        {
          "Rank": 20,
          "PlayerId": 260513,
          "Name": "Unstoppable Brandao",
          "Level": 71,
          "Experience": 737719
        },
        {
          "Rank": 21,
          "PlayerId": 9662,
          "Name": "Painkiller",
          "Level": 71,
          "Experience": 712579
        },
        {
          "Rank": 22,
          "PlayerId": 356559,
          "Name": "TodMip",
          "Level": 71,
          "Experience": 686550
        },
        {
          "Rank": 23,
          "PlayerId": 25175,
          "Name": "Unstoppable Reirok",
          "Level": 71,
          "Experience": 684145
        },
        {
          "Rank": 24,
          "PlayerId": 273372,
          "Name": "Siicker",
          "Level": 71,
          "Experience": 675598
        },
        {
          "Rank": 25,
          "PlayerId": 263705,
          "Name": "papitafrita",
          "Level": 70,
          "Experience": 657364
        },
        {
          "Rank": 26,
          "PlayerId": 316433,
          "Name": "reymonjsc",
          "Level": 70,
          "Experience": 617294
        },
        {
          "Rank": 27,
          "PlayerId": 273255,
          "Name": "MorilIa",
          "Level": 70,
          "Experience": 611563
        },
        {
          "Rank": 28,
          "PlayerId": 264699,
          "Name": "Stefanykiller",
          "Level": 70,
          "Experience": 610864
        },
        {
          "Rank": 29,
          "PlayerId": 4520,
          "Name": "MeDeixa",
          "Level": 69,
          "Experience": 602476
        },
        {
          "Rank": 30,
          "PlayerId": 326676,
          "Name": "Paladino of Poder",
          "Level": 69,
          "Experience": 594425
        },
        {
          "Rank": 31,
          "PlayerId": 248590,
          "Name": "killzero",
          "Level": 69,
          "Experience": 567191
        },
        {
          "Rank": 32,
          "PlayerId": 355073,
          "Name": "Reziel",
          "Level": 69,
          "Experience": 567168
        },
        {
          "Rank": 33,
          "PlayerId": 355513,
          "Name": "Saci De Patinetii",
          "Level": 69,
          "Experience": 559995
        },
        {
          "Rank": 34,
          "PlayerId": 321116,
          "Name": "Tirion The Zeruko",
          "Level": 69,
          "Experience": 547270
        },
        {
          "Rank": 35,
          "PlayerId": 356844,
          "Name": "TonyAi",
          "Level": 68,
          "Experience": 525002
        },
        {
          "Rank": 36,
          "PlayerId": 265774,
          "Name": "WanhedaDrago",
          "Level": 68,
          "Experience": 524430
        },
        {
          "Rank": 37,
          "PlayerId": 243241,
          "Name": "Abelito",
          "Level": 68,
          "Experience": 503992
        },
        {
          "Rank": 38,
          "PlayerId": 278413,
          "Name": "Tokiio",
          "Level": 68,
          "Experience": 499853
        },
        {
          "Rank": 39,
          "PlayerId": 253169,
          "Name": "Zkhorpion",
          "Level": 68,
          "Experience": 495077
        },
        {
          "Rank": 40,
          "PlayerId": 270079,
          "Name": "Goldencoin",
          "Level": 68,
          "Experience": 487078
        },
        {
          "Rank": 41,
          "PlayerId": 27448,
          "Name": "Ahmaneth",
          "Level": 68,
          "Experience": 484413
        },
        {
          "Rank": 42,
          "PlayerId": 22708,
          "Name": "Ashezinha",
          "Level": 68,
          "Experience": 483309
        },
        {
          "Rank": 43,
          "PlayerId": 291193,
          "Name": "Krynn",
          "Level": 67,
          "Experience": 454532
        },
        {
          "Rank": 44,
          "PlayerId": 257439,
          "Name": "skiees",
          "Level": 67,
          "Experience": 438510
        },
        {
          "Rank": 45,
          "PlayerId": 314759,
          "Name": "Brisadin",
          "Level": 67,
          "Experience": 438151
        },
        {
          "Rank": 46,
          "PlayerId": 4755,
          "Name": "IlIIIIII",
          "Level": 67,
          "Experience": 435226
        },
        {
          "Rank": 47,
          "PlayerId": 314227,
          "Name": "DARiL DIXON",
          "Level": 66,
          "Experience": 414476
        },
        {
          "Rank": 48,
          "PlayerId": 349926,
          "Name": "Conde Olaff",
          "Level": 66,
          "Experience": 398054
        },
        {
          "Rank": 49,
          "PlayerId": 14894,
          "Name": "Pretoriano",
          "Level": 66,
          "Experience": 394996
        },
        {
          "Rank": 50,
          "PlayerId": 276170,
          "Name": "Starry",
          "Level": 66,
          "Experience": 394503
        }
      ],
      "Taming": [
        {
          "Rank": 1,
          "PlayerId": 4641,
          "Name": "Seyuki",
          "Level": 74,
          "Experience": 2397250
        },
        {
          "Rank": 2,
          "PlayerId": 248907,
          "Name": "EvacinPro",
          "Level": 63,
          "Experience": 759775
        },
        {
          "Rank": 3,
          "PlayerId": 4565,
          "Name": "Sir Black",
          "Level": 62,
          "Experience": 665850
        },
        {
          "Rank": 4,
          "PlayerId": 344475,
          "Name": "Rott",
          "Level": 61,
          "Experience": 583523
        },
        {
          "Rank": 5,
          "PlayerId": 4552,
          "Name": "Tsukuyomi",
          "Level": 61,
          "Experience": 568044
        },
        {
          "Rank": 6,
          "PlayerId": 262903,
          "Name": "Darkbaxie",
          "Level": 60,
          "Experience": 534839
        },
        {
          "Rank": 7,
          "PlayerId": 25730,
          "Name": "Warlord Oliveira",
          "Level": 60,
          "Experience": 514659
        },
        {
          "Rank": 8,
          "PlayerId": 355073,
          "Name": "Reziel",
          "Level": 59,
          "Experience": 456673
        },
        {
          "Rank": 9,
          "PlayerId": 275952,
          "Name": "Demonix",
          "Level": 59,
          "Experience": 453404
        },
        {
          "Rank": 10,
          "PlayerId": 248791,
          "Name": "Migeehz",
          "Level": 59,
          "Experience": 451580
        },
        {
          "Rank": 11,
          "PlayerId": 260671,
          "Name": "Rellikk",
          "Level": 59,
          "Experience": 442169
        },
        {
          "Rank": 12,
          "PlayerId": 14253,
          "Name": "Aaunn",
          "Level": 58,
          "Experience": 426277
        },
        {
          "Rank": 13,
          "PlayerId": 347251,
          "Name": "LIRǟnzɛsLIxD",
          "Level": 58,
          "Experience": 422326
        },
        {
          "Rank": 14,
          "PlayerId": 333670,
          "Name": "Louco Perigoso",
          "Level": 58,
          "Experience": 403251
        },
        {
          "Rank": 15,
          "PlayerId": 246441,
          "Name": "DAYA",
          "Level": 57,
          "Experience": 382652
        },
        {
          "Rank": 16,
          "PlayerId": 11924,
          "Name": "MARECHALIGRISs",
          "Level": 57,
          "Experience": 371531
        },
        {
          "Rank": 17,
          "PlayerId": 5463,
          "Name": "te comi",
          "Level": 56,
          "Experience": 335255
        },
        {
          "Rank": 18,
          "PlayerId": 21192,
          "Name": "zkweF",
          "Level": 56,
          "Experience": 333468
        },
        {
          "Rank": 19,
          "PlayerId": 4560,
          "Name": "buKyk",
          "Level": 56,
          "Experience": 327067
        },
        {
          "Rank": 20,
          "PlayerId": 4745,
          "Name": "Eldermolidor",
          "Level": 56,
          "Experience": 305619
        },
        {
          "Rank": 21,
          "PlayerId": 243315,
          "Name": "teilor",
          "Level": 56,
          "Experience": 304591
        },
        {
          "Rank": 22,
          "PlayerId": 9662,
          "Name": "Painkiller",
          "Level": 55,
          "Experience": 299396
        },
        {
          "Rank": 23,
          "PlayerId": 256753,
          "Name": "GANDALFFF",
          "Level": 55,
          "Experience": 298650
        },
        {
          "Rank": 24,
          "PlayerId": 7063,
          "Name": "Unstoppable Guuh Zikaah",
          "Level": 55,
          "Experience": 292966
        },
        {
          "Rank": 25,
          "PlayerId": 11530,
          "Name": "Stenffor",
          "Level": 55,
          "Experience": 292954
        },
        {
          "Rank": 26,
          "PlayerId": 248457,
          "Name": "angelmathias",
          "Level": 55,
          "Experience": 284850
        },
        {
          "Rank": 27,
          "PlayerId": 331661,
          "Name": "Monstrao",
          "Level": 55,
          "Experience": 282046
        },
        {
          "Rank": 28,
          "PlayerId": 284765,
          "Name": "Amateratsu",
          "Level": 55,
          "Experience": 281914
        },
        {
          "Rank": 29,
          "PlayerId": 260513,
          "Name": "Unstoppable Brandao",
          "Level": 55,
          "Experience": 274315
        },
        {
          "Rank": 30,
          "PlayerId": 318610,
          "Name": "Rama",
          "Level": 54,
          "Experience": 267843
        },
        {
          "Rank": 31,
          "PlayerId": 4611,
          "Name": "lIlIlIlI",
          "Level": 54,
          "Experience": 266111
        },
        {
          "Rank": 32,
          "PlayerId": 6109,
          "Name": "J O T A",
          "Level": 54,
          "Experience": 261887
        },
        {
          "Rank": 33,
          "PlayerId": 6368,
          "Name": "Unstoppable Nunoh",
          "Level": 54,
          "Experience": 258918
        },
        {
          "Rank": 34,
          "PlayerId": 361160,
          "Name": "Biridim Streamer",
          "Level": 54,
          "Experience": 251103
        },
        {
          "Rank": 35,
          "PlayerId": 246166,
          "Name": "nanzin",
          "Level": 54,
          "Experience": 246146
        },
        {
          "Rank": 36,
          "PlayerId": 356844,
          "Name": "TonyAi",
          "Level": 54,
          "Experience": 244323
        },
        {
          "Rank": 37,
          "PlayerId": 269283,
          "Name": "Jet Lag",
          "Level": 54,
          "Experience": 242073
        },
        {
          "Rank": 38,
          "PlayerId": 249534,
          "Name": "Wolfer",
          "Level": 53,
          "Experience": 232523
        },
        {
          "Rank": 39,
          "PlayerId": 362485,
          "Name": "Khaziks",
          "Level": 53,
          "Experience": 229504
        },
        {
          "Rank": 40,
          "PlayerId": 14767,
          "Name": "Lord Mandy Kai",
          "Level": 53,
          "Experience": 224661
        },
        {
          "Rank": 41,
          "PlayerId": 279224,
          "Name": "DemonicAV",
          "Level": 53,
          "Experience": 224586
        },
        {
          "Rank": 42,
          "PlayerId": 263705,
          "Name": "papitafrita",
          "Level": 53,
          "Experience": 222788
        },
        {
          "Rank": 43,
          "PlayerId": 347001,
          "Name": "Stay Awake",
          "Level": 53,
          "Experience": 222736
        },
        {
          "Rank": 44,
          "PlayerId": 278698,
          "Name": "Zynthrox",
          "Level": 53,
          "Experience": 222556
        },
        {
          "Rank": 45,
          "PlayerId": 298742,
          "Name": "joseguevami",
          "Level": 53,
          "Experience": 217828
        },
        {
          "Rank": 46,
          "PlayerId": 8659,
          "Name": "Wezermoo",
          "Level": 52,
          "Experience": 212962
        },
        {
          "Rank": 47,
          "PlayerId": 4781,
          "Name": "GRETTEL",
          "Level": 52,
          "Experience": 208564
        },
        {
          "Rank": 48,
          "PlayerId": 316433,
          "Name": "reymonjsc",
          "Level": 52,
          "Experience": 206379
        },
        {
          "Rank": 49,
          "PlayerId": 27448,
          "Name": "Ahmaneth",
          "Level": 52,
          "Experience": 205908
        },
        {
          "Rank": 50,
          "PlayerId": 22708,
          "Name": "Ashezinha",
          "Level": 52,
          "Experience": 205405
        }
      ]
    }
  }
}